Metadata-Version: 1.1
Name: openerp-l10n-lu
Version: 7.0.355
Summary: Luxembourg - Accounting
Home-page: http://www.openerp.com http://www.adn-luxembourg.com
Author: OpenERP SA & ADN
Author-email: TODO
License: AGPL-3
Platform: UNKNOWN
Classifier: Development Status :: 5 - Production/Stable
Classifier: Environment :: Plugins
Classifier: Intended Audience :: Developers
Classifier: License :: OSI Approved :: GNU Affero General Public License v3
Classifier: Natural Language :: English
Classifier: Programming Language :: Python :: 2.7
Classifier: Programming Language :: Python :: Implementation :: CPython
